demodemo/__init__.py
demodemo-0.0.1.dist-info/LICENCE.txt
demodemo-0.0.1.dist-info/METADATA
demodemo-0.0.1.dist-info/WHEEL
demodemo-0.0.1.dist-info/top_level.txt
demodemo-0.0.1.dist-info/RECORD
