Metadata-Version: 2.1
Name: demodemo
Version: 0.0.1
Summary: A Smiple MsSql API
Home-page: UNKNOWN
Author: Murali Tharan S
Author-email: muralififa@gmail.com
License: MIT
Keywords: SQL,MsSql,SQL using python,Pyodbc,SQL Connection
Platform: UNKNOWN
Classifier: Development Status :: 5 - Production/Stable
Classifier: Intended Audience :: Education
Classifier: Operating System :: Microsoft :: Windows :: Windows 10
Classifier: License :: OSI Approved :: MIT License
Classifier: Programming Language :: Python :: 3
License-File: LICENCE.txt
